fastwlk/__init__.py
fastwlk/kernel.py
fastwlk/utils/exception.py
fastwlk/utils/functions.py
fastwlk/utils/validation.py
fastwlk-0.2.14.dist-info/LICENSE
fastwlk-0.2.14.dist-info/WHEEL
fastwlk-0.2.14.dist-info/METADATA
fastwlk-0.2.14.dist-info/RECORD
